simeon/__init__.py
simeon/__main__.py
simeon/download/__init__.py
simeon/download/aws.py
simeon/download/emails.py
simeon/download/logs.py
simeon/download/sqls.py
simeon/download/utilities.py
simeon/exceptions/__init__.py
simeon/report/__init__.py
simeon/report/utilities.py
simeon/report/queries/chapter_grades.sql
simeon/report/queries/course_item.sql
simeon/report/queries/course_modal_agent.sql
simeon/report/queries/course_modal_ip.sql
simeon/report/queries/course_modal_language.sql
simeon/report/queries/course_problem.sql
simeon/report/queries/enrollday_all.sql
simeon/report/queries/enrollment_events.sql
simeon/report/queries/forum_events.sql
simeon/report/queries/forum_person.sql
simeon/report/queries/forum_posts.sql
simeon/report/queries/language_multi_transcripts.sql
simeon/report/queries/ora_events.sql
simeon/report/queries/pc_day_agent_counts.sql
simeon/report/queries/pc_day_ip_counts.sql
simeon/report/queries/pc_day_totals.sql
simeon/report/queries/pc_day_trlang.sql
simeon/report/queries/pc_forum.sql
simeon/report/queries/pc_nchapters.sql
simeon/report/queries/pc_video_watched.sql
simeon/report/queries/person_course.sql
simeon/report/queries/person_course_day.sql
simeon/report/queries/person_enrollment_verified.sql
simeon/report/queries/person_item.sql
simeon/report/queries/person_problem.sql
simeon/report/queries/problem_check.sql
simeon/report/queries/problem_grades.sql
simeon/report/queries/show_answer.sql
simeon/report/queries/show_answer_stats_by_course.sql
simeon/report/queries/show_answer_stats_by_user.sql
simeon/report/queries/time_on_asset_daily.sql
simeon/report/queries/time_on_asset_totals.sql
simeon/report/queries/time_on_task.sql
simeon/report/queries/time_on_task_totals.sql
simeon/report/queries/video_axis.sql
simeon/report/queries/video_stats_day.sql
simeon/scripts/__init__.py
simeon/scripts/geoip.py
simeon/scripts/simeon.py
simeon/scripts/utilities.py
simeon/scripts/youtube.py
simeon/scripts/data/geographic_regions_by_country.csv
simeon-0.0.26.dist-info/licenses/LICENSE
simeon-0.0.26.dist-info/METADATA
simeon-0.0.26.dist-info/WHEEL
simeon-0.0.26.dist-info/entry_points.txt
simeon-0.0.26.dist-info/top_level.txt
simeon-0.0.26.dist-info/RECORD
