Metadata-Version: 2.4
Name: simeon
Version: 0.0.26
Summary: A CLI tool to help process research data from edX
Home-page: https://github.com/MIT-IR/simeon
Author: MIT Institutional Research
Author-email: MIT Institutional Research <irx@mit.edu>
License: MIT License
Project-URL: Homepage, https://github.com/MIT-IR/simeon
Project-URL: Bug Tracker, https://github.com/MIT-IR/simeon/issues
Project-URL: Documentation, https://mit-ir.github.io/simeon/
Keywords: research,edx,MOOC,education,online-learning
Classifier: Development Status :: 4 - Beta
Classifier: Environment :: Console
Classifier: Intended Audience :: Science/Research
Classifier: Natural Language :: English
Classifier: License :: OSI Approved :: MIT License
Classifier: Programming Language :: Python
Classifier: Programming Language :: Python :: 3
Classifier: Programming Language :: Python :: 3.6
Classifier: Programming Language :: Python :: 3.7
Classifier: Programming Language :: Python :: 3.8
Classifier: Programming Language :: Python :: 3.9
Classifier: Programming Language :: Python :: 3.10
Classifier: Programming Language :: Python :: 3.11
Classifier: Programming Language :: Python :: 3.12
Classifier: Programming Language :: Python :: 3.13
Classifier: Programming Language :: Python :: Implementation :: CPython
Classifier: Topic :: Text Processing
Requires-Python: >=3.6
License-File: LICENSE
Requires-Dist: boto3>=1.16.57
Requires-Dist: google-cloud-bigquery>=2.6.2
Requires-Dist: google-cloud-storage>=1.35.0
Requires-Dist: jinja2
Requires-Dist: python-dateutil>=2.8.1
Provides-Extra: geoip
Requires-Dist: geoip2; extra == "geoip"
Provides-Extra: test
Requires-Dist: black; extra == "test"
Requires-Dist: isort; extra == "test"
Requires-Dist: tox; extra == "test"
Provides-Extra: dev
Requires-Dist: black; extra == "dev"
Requires-Dist: isort; extra == "dev"
Requires-Dist: pip-tools; extra == "dev"
Requires-Dist: sphinx; extra == "dev"
Requires-Dist: sphinx-material; extra == "dev"
Requires-Dist: tox; extra == "dev"
Provides-Extra: docs
Requires-Dist: sphinx; extra == "docs"
Requires-Dist: sphinx-material; extra == "docs"
Dynamic: author
Dynamic: home-page
Dynamic: license-file
Dynamic: requires-python
